README.txt
setup.py
textblockomator.py
textblockomator.egg-info/PKG-INFO
textblockomator.egg-info/SOURCES.txt
textblockomator.egg-info/dependency_links.txt
textblockomator.egg-info/requires.txt
textblockomator.egg-info/top_level.txt