Metadata-Version: 1.0
Name: textblockomator
Version: 0.2
Summary: Listens for keywords and prints out blocks of text
Home-page: UNKNOWN
Author: Joseph Jones
Author-email: jjones15470@gmail.com
License: UNKNOWN
Platform: UNKNOWN
